gas_station_spain_api/__init__.py
gas_station_spain_api/const.py
gas_station_spain_api/gas_station.py
gas_station_spain_api-1.2.dist-info/LICENSE
gas_station_spain_api-1.2.dist-info/METADATA
gas_station_spain_api-1.2.dist-info/WHEEL
gas_station_spain_api-1.2.dist-info/RECORD
