Metadata-Version: 2.3
Name: gas-station-spain-api
Version: 1.2
Summary: Obtiene el precio actual del combustible en las distintas gasolineras de España
License: MIT
Author: Miguel Ángel López
Author-email: miguel.angel.lopez.vicente@gmail.com
Requires-Python: >3.9
Classifier: License :: OSI Approved :: MIT License
Classifier: Programming Language :: Python :: 3
Classifier: Programming Language :: Python :: 3.10
Classifier: Programming Language :: Python :: 3.11
Classifier: Programming Language :: Python :: 3.12
Classifier: Programming Language :: Python :: 3.13
Requires-Dist: aiohttp (>=3.7.4.post0)
Requires-Dist: async_timeout (>=3.0.1)
Requires-Dist: pytest (>=8.3.5)
Requires-Dist: tenacity (>=9.0.0)
